{
	"C_Recoil_K98": {
		"@Remaining": 4,
		"@SuperName": "Class",
		"@TemplateName": "Default__CurveVector",
		"ClassName": "CurveVector",
		"ExportName": "C_Recoil_K98",
		"FloatCurves": {
			"Keys": [
				{
					"StrucName": "RichCurveKey",
					"value": {
						"ArriveTangent": 0,
						"ArriveTangentWeight": 0,
						"InterpMode": 2,
						"LeaveTangent": 0,
						"LeaveTangentWeight": 0,
						"StrucName": "FRichCurveKey",
						"TangentMode": 0,
						"TangentWeightMode": 0,
						"Time": 0.00229883939,
						"Value": 0
					}
				},
				{
					"StrucName": "RichCurveKey",
					"value": {
						"ArriveTangent": 0.107400805,
						"ArriveTangentWeight": 0,
						"InterpMode": 2,
						"LeaveTangent": 0.10740269,
						"LeaveTangentWeight": 0,
						"StrucName": "FRichCurveKey",
						"TangentMode": 1,
						"TangentWeightMode": 0,
						"Time": 1.05886352,
						"Value": 0.154542208
					}
				},
				{
					"StrucName": "RichCurveKey",
					"value": {
						"ArriveTangent": 0.556422532,
						"ArriveTangentWeight": 0,
						"InterpMode": 2,
						"LeaveTangent": 0.556422532,
						"LeaveTangentWeight": 0,
						"StrucName": "FRichCurveKey",
						"TangentMode": 1,
						"TangentWeightMode": 0,
						"Time": 2.66770887,
						"Value": 1.01701641
					}
				},
				{
					"StrucName": "RichCurveKey",
					"value": {
						"ArriveTangent": 0.110613704,
						"ArriveTangentWeight": 0,
						"InterpMode": 2,
						"LeaveTangent": 0.110610574,
						"LeaveTangentWeight": 0,
						"StrucName": "FRichCurveKey",
						"TangentMode": 1,
						"TangentWeightMode": 0,
						"Time": 4.74038,
						"Value": 1.10697114
					}
				}
			],
			"StrucName": "RichCurve"
		},
		"__FloatCurves_1": {
			"Keys": [
				{
					"StrucName": "RichCurveKey",
					"value": {
						"ArriveTangent": 0,
						"ArriveTangentWeight": 0,
						"InterpMode": 2,
						"LeaveTangent": 0,
						"LeaveTangentWeight": 0,
						"StrucName": "FRichCurveKey",
						"TangentMode": 0,
						"TangentWeightMode": 0,
						"Time": -0.00414299965,
						"Value": 0.231786847
					}
				},
				{
					"StrucName": "RichCurveKey",
					"value": {
						"ArriveTangent": 0.4185619,
						"ArriveTangentWeight": 0,
						"InterpMode": 2,
						"LeaveTangent": 0.4185619,
						"LeaveTangentWeight": 0,
						"StrucName": "FRichCurveKey",
						"TangentMode": 0,
						"TangentWeightMode": 0,
						"Time": 0.2945528,
						"Value": 0.131786823
					}
				},
				{
					"StrucName": "RichCurveKey",
					"value": {
						"ArriveTangent": 0.4025589,
						"ArriveTangentWeight": 0,
						"InterpMode": 2,
						"LeaveTangent": 0.402556866,
						"LeaveTangentWeight": 0,
						"StrucName": "FRichCurveKey",
						"TangentMode": 1,
						"TangentWeightMode": 0,
						"Time": 1.9390353,
						"Value": 1.04512727
					}
				},
				{
					"StrucName": "RichCurveKey",
					"value": {
						"ArriveTangent": 0.167732373,
						"ArriveTangentWeight": 0,
						"InterpMode": 2,
						"LeaveTangent": 0.167733461,
						"LeaveTangentWeight": 0,
						"StrucName": "FRichCurveKey",
						"TangentMode": 1,
						"TangentWeightMode": 0,
						"Time": 3.5,
						"Value": 1.34144437
					}
				},
				{
					"StrucName": "RichCurveKey",
					"value": {
						"ArriveTangent": 0,
						"ArriveTangentWeight": 0,
						"InterpMode": 2,
						"LeaveTangent": -0.303860158,
						"LeaveTangentWeight": 0,
						"StrucName": "FRichCurveKey",
						"TangentMode": 0,
						"TangentWeightMode": 0,
						"Time": 4.390445,
						"Value": 0.7352114
					}
				}
			],
			"StrucName": "RichCurve"
		},
		"__FloatCurves_2": {
			"Keys": [
				{
					"StrucName": "RichCurveKey",
					"value": {
						"ArriveTangent": 0,
						"ArriveTangentWeight": 0,
						"InterpMode": 2,
						"LeaveTangent": 0,
						"LeaveTangentWeight": 0,
						"StrucName": "FRichCurveKey",
						"TangentMode": 0,
						"TangentWeightMode": 0,
						"Time": 0.00229883939,
						"Value": 0
					}
				},
				{
					"StrucName": "RichCurveKey",
					"value": {
						"ArriveTangent": 0,
						"ArriveTangentWeight": 0,
						"InterpMode": 0,
						"LeaveTangent": 0,
						"LeaveTangentWeight": 0,
						"StrucName": "FRichCurveKey",
						"TangentMode": 0,
						"TangentWeightMode": 0,
						"Time": 3.28919578,
						"Value": 1.773539
					}
				}
			],
			"StrucName": "RichCurve"
		}
	}
}